{"date":"2026-06-13","station":"62118076","rows":[{"time":"2026-06-13 00:00:00","production_kw":0.002,"consumption_kw":0.36,"grid_kw":0.02,"battery_kw":0.485,"soc_pct":33.0,"pv_kw":0.002,"generator_kw":0,"grid_inverter_kw":0},{"time":"2026-06-13 00:05:00","production_kw":0.002,"consumption_kw":0.34,"grid_kw":0.0,"battery_kw":0.49,"soc_pct":33.0,"pv_kw":0.002,"generator_kw":0,"grid_inverter_kw":0},{"time":"2026-06-13 00:10:00","production_kw":0.002,"consumption_kw":0.36,"grid_kw":0.02,"battery_kw":0.473,"soc_pct":33.0,"pv_kw":0.002,"generator_kw":0,"grid_inverter_kw":0},{"time":"2026-06-13 00:15:00","production_kw":0.002,"consumption_kw":0.36,"grid_kw":0.02,"battery_kw":0.487,"soc_pct":33.0,"pv_kw":0.002,"generator_kw":0,"grid_inverter_kw":0},{"time":"2026-06-13 00:20:00","production_kw":0.002,"consumption_kw":0.34,"grid_kw":0.0,"battery_kw":0.48,"soc_pct":32.0,"pv_kw":0.002,"generator_kw":0,"grid_inverter_kw":0},{"time":"2026-06-13 00:25:00","production_kw":0.002,"consumption_kw":0.36,"grid_kw":0.02,"battery_kw":0.487,"soc_pct":32.0,"pv_kw":0.002,"generator_kw":0,"grid_inverter_kw":0},{"time":"2026-06-13 00:30:00","production_kw":0.002,"consumption_kw":0.44,"grid_kw":0.02,"battery_kw":0.556,"soc_pct":32.0,"pv_kw":0.002,"generator_kw":0,"grid_inverter_kw":0},{"time":"2026-06-13 00:35:00","production_kw":0.002,"consumption_kw":0.38,"grid_kw":0.02,"battery_kw":0.502,"soc_pct":32.0,"pv_kw":0.002,"generator_kw":0,"grid_inverter_kw":0},{"time":"2026-06-13 00:40:00","production_kw":0.002,"consumption_kw":0.35,"grid_kw":0.0,"battery_kw":0.493,"soc_pct":31.0,"pv_kw":0.002,"generator_kw":0,"grid_inverter_kw":0},{"time":"2026-06-13 00:45:00","production_kw":0.002,"consumption_kw":0.5,"grid_kw":0.0,"battery_kw":0.64,"soc_pct":31.0,"pv_kw":0.002,"generator_kw":0,"grid_inverter_kw":0},{"time":"2026-06-13 00:50:00","production_kw":0.002,"consumption_kw":0.5,"grid_kw":0.02,"battery_kw":0.619,"soc_pct":31.0,"pv_kw":0.002,"generator_kw":0,"grid_inverter_kw":0},{"time":"2026-06-13 00:55:00","production_kw":0.002,"consumption_kw":0.5,"grid_kw":0.56,"battery_kw":0.076,"soc_pct":30.0,"pv_kw":0.002,"generator_kw":0,"grid_inverter_kw":0},{"time":"2026-06-13 01:00:00","production_kw":0.002,"consumption_kw":0.49,"grid_kw":0.55,"battery_kw":0.077,"soc_pct":30.0,"pv_kw":0.002,"generator_kw":0,"grid_inverter_kw":0},{"time":"2026-06-13 01:05:00","production_kw":0.002,"consumption_kw":0.49,"grid_kw":0.55,"battery_kw":0.074,"soc_pct":30.0,"pv_kw":0.002,"generator_kw":0,"grid_inverter_kw":0},{"time":"2026-06-13 01:10:00","production_kw":0.002,"consumption_kw":0.35,"grid_kw":0.41,"battery_kw":0.076,"soc_pct":30.0,"pv_kw":0.002,"generator_kw":0,"grid_inverter_kw":0},{"time":"2026-06-13 01:15:00","production_kw":0.002,"consumption_kw":0.36,"grid_kw":0.42,"battery_kw":0.077,"soc_pct":30.0,"pv_kw":0.002,"generator_kw":0,"grid_inverter_kw":0},{"time":"2026-06-13 01:20:00","production_kw":0.002,"consumption_kw":0.35,"grid_kw":0.41,"battery_kw":0.077,"soc_pct":30.0,"pv_kw":0.002,"generator_kw":0,"grid_inverter_kw":0},{"time":"2026-06-13 01:25:00","production_kw":0.002,"consumption_kw":0.35,"grid_kw":0.41,"battery_kw":0.076,"soc_pct":30.0,"pv_kw":0.002,"generator_kw":0,"grid_inverter_kw":0},{"time":"2026-06-13 01:30:00","production_kw":0.003,"consumption_kw":0.35,"grid_kw":0.42,"battery_kw":0.075,"soc_pct":30.0,"pv_kw":0.003,"generator_kw":0,"grid_inverter_kw":0},{"time":"2026-06-13 01:35:00","production_kw":0.002,"consumption_kw":0.34,"grid_kw":0.41,"battery_kw":0.078,"soc_pct":30.0,"pv_kw":0.002,"generator_kw":0,"grid_inverter_kw":0},{"time":"2026-06-13 01:40:00","production_kw":0.003,"consumption_kw":0.34,"grid_kw":0.41,"battery_kw":0.079,"soc_pct":30.0,"pv_kw":0.003,"generator_kw":0,"grid_inverter_kw":0},{"time":"2026-06-13 01:45:00","production_kw":0.002,"consumption_kw":0.34,"grid_kw":0.41,"battery_kw":0.074,"soc_pct":30.0,"pv_kw":0.002,"generator_kw":0,"grid_inverter_kw":0},{"time":"2026-06-13 01:50:00","production_kw":0.002,"consumption_kw":0.34,"grid_kw":0.41,"battery_kw":0.073,"soc_pct":30.0,"pv_kw":0.002,"generator_kw":0,"grid_inverter_kw":0},{"time":"2026-06-13 01:55:00","production_kw":0.003,"consumption_kw":0.35,"grid_kw":0.42,"battery_kw":0.076,"soc_pct":30.0,"pv_kw":0.003,"generator_kw":0,"grid_inverter_kw":0},{"time":"2026-06-13 02:00:00","production_kw":0.003,"consumption_kw":0.36,"grid_kw":0.42,"battery_kw":0.075,"soc_pct":30.0,"pv_kw":0.003,"generator_kw":0,"grid_inverter_kw":0},{"time":"2026-06-13 02:05:00","production_kw":0.003,"consumption_kw":0.35,"grid_kw":0.42,"battery_kw":0.078,"soc_pct":30.0,"pv_kw":0.003,"generator_kw":0,"grid_inverter_kw":0},{"time":"2026-06-13 02:10:00","production_kw":0.003,"consumption_kw":0.35,"grid_kw":0.41,"battery_kw":0.079,"soc_pct":30.0,"pv_kw":0.003,"generator_kw":0,"grid_inverter_kw":0},{"time":"2026-06-13 02:15:00","production_kw":0.003,"consumption_kw":0.34,"grid_kw":0.41,"battery_kw":0.077,"soc_pct":30.0,"pv_kw":0.003,"generator_kw":0,"grid_inverter_kw":0},{"time":"2026-06-13 02:20:00","production_kw":0.003,"consumption_kw":0.35,"grid_kw":0.41,"battery_kw":0.074,"soc_pct":30.0,"pv_kw":0.003,"generator_kw":0,"grid_inverter_kw":0},{"time":"2026-06-13 02:25:00","production_kw":0.003,"consumption_kw":0.35,"grid_kw":0.41,"battery_kw":0.076,"soc_pct":30.0,"pv_kw":0.003,"generator_kw":0,"grid_inverter_kw":0},{"time":"2026-06-13 02:30:00","production_kw":0.003,"consumption_kw":0.49,"grid_kw":0.55,"battery_kw":0.075,"soc_pct":30.0,"pv_kw":0.003,"generator_kw":0,"grid_inverter_kw":0},{"time":"2026-06-13 02:35:00","production_kw":0.003,"consumption_kw":0.42,"grid_kw":0.48,"battery_kw":0.074,"soc_pct":30.0,"pv_kw":0.003,"generator_kw":0,"grid_inverter_kw":0},{"time":"2026-06-13 02:40:00","production_kw":0.003,"consumption_kw":0.42,"grid_kw":0.48,"battery_kw":0.074,"soc_pct":30.0,"pv_kw":0.003,"generator_kw":0,"grid_inverter_kw":0},{"time":"2026-06-13 02:45:00","production_kw":0.003,"consumption_kw":0.42,"grid_kw":0.48,"battery_kw":0.077,"soc_pct":30.0,"pv_kw":0.003,"generator_kw":0,"grid_inverter_kw":0},{"time":"2026-06-13 02:50:00","production_kw":0.003,"consumption_kw":0.41,"grid_kw":0.48,"battery_kw":0.076,"soc_pct":30.0,"pv_kw":0.003,"generator_kw":0,"grid_inverter_kw":0},{"time":"2026-06-13 02:55:00","production_kw":0.003,"consumption_kw":0.41,"grid_kw":0.48,"battery_kw":0.077,"soc_pct":30.0,"pv_kw":0.003,"generator_kw":0,"grid_inverter_kw":0},{"time":"2026-06-13 03:00:00","production_kw":0.003,"consumption_kw":0.41,"grid_kw":0.47,"battery_kw":0.077,"soc_pct":30.0,"pv_kw":0.003,"generator_kw":0,"grid_inverter_kw":0},{"time":"2026-06-13 03:05:00","production_kw":0.003,"consumption_kw":0.27,"grid_kw":0.34,"battery_kw":0.079,"soc_pct":30.0,"pv_kw":0.003,"generator_kw":0,"grid_inverter_kw":0},{"time":"2026-06-13 03:10:00","production_kw":0.002,"consumption_kw":0.28,"grid_kw":0.34,"battery_kw":0.076,"soc_pct":30.0,"pv_kw":0.002,"generator_kw":0,"grid_inverter_kw":0},{"time":"2026-06-13 03:15:00","production_kw":0.003,"consumption_kw":0.29,"grid_kw":0.35,"battery_kw":0.078,"soc_pct":30.0,"pv_kw":0.003,"generator_kw":0,"grid_inverter_kw":0},{"time":"2026-06-13 03:20:00","production_kw":0.003,"consumption_kw":0.3,"grid_kw":0.37,"battery_kw":0.08,"soc_pct":30.0,"pv_kw":0.003,"generator_kw":0,"grid_inverter_kw":0},{"time":"2026-06-13 03:25:00","production_kw":0.003,"consumption_kw":0.31,"grid_kw":0.37,"battery_kw":0.082,"soc_pct":30.0,"pv_kw":0.003,"generator_kw":0,"grid_inverter_kw":0},{"time":"2026-06-13 03:30:00","production_kw":0.003,"consumption_kw":0.44,"grid_kw":0.51,"battery_kw":0.075,"soc_pct":30.0,"pv_kw":0.003,"generator_kw":0,"grid_inverter_kw":0},{"time":"2026-06-13 03:35:00","production_kw":0.003,"consumption_kw":0.44,"grid_kw":0.5,"battery_kw":0.077,"soc_pct":30.0,"pv_kw":0.003,"generator_kw":0,"grid_inverter_kw":0},{"time":"2026-06-13 03:40:00","production_kw":0.003,"consumption_kw":0.51,"grid_kw":0.57,"battery_kw":0.076,"soc_pct":30.0,"pv_kw":0.003,"generator_kw":0,"grid_inverter_kw":0},{"time":"2026-06-13 03:45:00","production_kw":0.003,"consumption_kw":0.53,"grid_kw":0.6,"battery_kw":0.078,"soc_pct":30.0,"pv_kw":0.003,"generator_kw":0,"grid_inverter_kw":0},{"time":"2026-06-13 03:50:00","production_kw":0.003,"consumption_kw":0.51,"grid_kw":0.58,"battery_kw":0.077,"soc_pct":30.0,"pv_kw":0.003,"generator_kw":0,"grid_inverter_kw":0},{"time":"2026-06-13 03:55:00","production_kw":0.003,"consumption_kw":0.34,"grid_kw":0.41,"battery_kw":0.077,"soc_pct":30.0,"pv_kw":0.003,"generator_kw":0,"grid_inverter_kw":0},{"time":"2026-06-13 04:00:00","production_kw":0.003,"consumption_kw":0.33,"grid_kw":0.0,"battery_kw":0.474,"soc_pct":29.0,"pv_kw":0.003,"generator_kw":0,"grid_inverter_kw":0},{"time":"2026-06-13 04:05:00","production_kw":0.003,"consumption_kw":0.32,"grid_kw":0.0,"battery_kw":0.466,"soc_pct":29.0,"pv_kw":0.003,"generator_kw":0,"grid_inverter_kw":0},{"time":"2026-06-13 04:10:00","production_kw":0.003,"consumption_kw":0.33,"grid_kw":0.0,"battery_kw":0.47,"soc_pct":29.0,"pv_kw":0.003,"generator_kw":0,"grid_inverter_kw":0},{"time":"2026-06-13 04:15:00","production_kw":0.003,"consumption_kw":0.47,"grid_kw":0.0,"battery_kw":0.607,"soc_pct":29.0,"pv_kw":0.003,"generator_kw":0,"grid_inverter_kw":0},{"time":"2026-06-13 04:20:00","production_kw":0.003,"consumption_kw":0.46,"grid_kw":0.0,"battery_kw":0.603,"soc_pct":28.0,"pv_kw":0.003,"generator_kw":0,"grid_inverter_kw":0},{"time":"2026-06-13 04:25:00","production_kw":0.003,"consumption_kw":0.46,"grid_kw":0.0,"battery_kw":0.601,"soc_pct":28.0,"pv_kw":0.003,"generator_kw":0,"grid_inverter_kw":0},{"time":"2026-06-13 04:30:00","production_kw":0.003,"consumption_kw":0.48,"grid_kw":0.02,"battery_kw":0.603,"soc_pct":28.0,"pv_kw":0.003,"generator_kw":0,"grid_inverter_kw":0},{"time":"2026-06-13 04:35:00","production_kw":0.003,"consumption_kw":0.34,"grid_kw":0.02,"battery_kw":0.463,"soc_pct":28.0,"pv_kw":0.003,"generator_kw":0,"grid_inverter_kw":0},{"time":"2026-06-13 04:40:00","production_kw":0.003,"consumption_kw":0.32,"grid_kw":0.0,"battery_kw":0.459,"soc_pct":27.0,"pv_kw":0.003,"generator_kw":0,"grid_inverter_kw":0},{"time":"2026-06-13 04:45:00","production_kw":0.003,"consumption_kw":0.32,"grid_kw":0.0,"battery_kw":0.461,"soc_pct":27.0,"pv_kw":0.003,"generator_kw":0,"grid_inverter_kw":0},{"time":"2026-06-13 04:50:00","production_kw":0.003,"consumption_kw":0.34,"grid_kw":0.02,"battery_kw":0.46,"soc_pct":27.0,"pv_kw":0.003,"generator_kw":0,"grid_inverter_kw":0},{"time":"2026-06-13 04:55:00","production_kw":0.003,"consumption_kw":0.34,"grid_kw":0.02,"battery_kw":0.46,"soc_pct":27.0,"pv_kw":0.003,"generator_kw":0,"grid_inverter_kw":0},{"time":"2026-06-13 05:00:00","production_kw":0.003,"consumption_kw":0.32,"grid_kw":0.0,"battery_kw":0.461,"soc_pct":26.0,"pv_kw":0.003,"generator_kw":0,"grid_inverter_kw":0},{"time":"2026-06-13 05:05:00","production_kw":0.003,"consumption_kw":0.47,"grid_kw":0.0,"battery_kw":0.607,"soc_pct":26.0,"pv_kw":0.003,"generator_kw":0,"grid_inverter_kw":0},{"time":"2026-06-13 05:10:00","production_kw":0.003,"consumption_kw":0.46,"grid_kw":0.0,"battery_kw":0.607,"soc_pct":26.0,"pv_kw":0.003,"generator_kw":0,"grid_inverter_kw":0},{"time":"2026-06-13 05:15:00","production_kw":0.003,"consumption_kw":0.47,"grid_kw":0.53,"battery_kw":0.076,"soc_pct":25.0,"pv_kw":0.003,"generator_kw":0,"grid_inverter_kw":0},{"time":"2026-06-13 05:20:00","production_kw":0.003,"consumption_kw":0.47,"grid_kw":0.54,"battery_kw":0.077,"soc_pct":25.0,"pv_kw":0.003,"generator_kw":0,"grid_inverter_kw":0},{"time":"2026-06-13 05:25:00","production_kw":0.003,"consumption_kw":0.34,"grid_kw":0.4,"battery_kw":0.084,"soc_pct":25.0,"pv_kw":0.003,"generator_kw":0,"grid_inverter_kw":0},{"time":"2026-06-13 05:30:00","production_kw":0.003,"consumption_kw":0.34,"grid_kw":0.4,"battery_kw":0.08,"soc_pct":25.0,"pv_kw":0.003,"generator_kw":0,"grid_inverter_kw":0},{"time":"2026-06-13 05:35:00","production_kw":0.003,"consumption_kw":0.26,"grid_kw":0.33,"battery_kw":0.073,"soc_pct":25.0,"pv_kw":0.003,"generator_kw":0,"grid_inverter_kw":0},{"time":"2026-06-13 05:40:00","production_kw":0.003,"consumption_kw":0.27,"grid_kw":0.33,"battery_kw":0.078,"soc_pct":25.0,"pv_kw":0.003,"generator_kw":0,"grid_inverter_kw":0},{"time":"2026-06-13 05:45:00","production_kw":0.003,"consumption_kw":0.26,"grid_kw":0.32,"battery_kw":0.076,"soc_pct":25.0,"pv_kw":0.003,"generator_kw":0,"grid_inverter_kw":0},{"time":"2026-06-13 05:50:00","production_kw":0.003,"consumption_kw":0.26,"grid_kw":0.32,"battery_kw":0.076,"soc_pct":25.0,"pv_kw":0.003,"generator_kw":0,"grid_inverter_kw":0},{"time":"2026-06-13 05:55:00","production_kw":0.003,"consumption_kw":0.26,"grid_kw":0.32,"battery_kw":0.078,"soc_pct":25.0,"pv_kw":0.003,"generator_kw":0,"grid_inverter_kw":0},{"time":"2026-06-13 06:00:00","production_kw":0.003,"consumption_kw":0.26,"grid_kw":0.33,"battery_kw":0.077,"soc_pct":25.0,"pv_kw":0.003,"generator_kw":0,"grid_inverter_kw":0},{"time":"2026-06-13 06:05:00","production_kw":0.003,"consumption_kw":0.26,"grid_kw":0.33,"battery_kw":0.078,"soc_pct":25.0,"pv_kw":0.003,"generator_kw":0,"grid_inverter_kw":0},{"time":"2026-06-13 06:10:00","production_kw":0.004,"consumption_kw":0.27,"grid_kw":0.33,"battery_kw":0.077,"soc_pct":25.0,"pv_kw":0.004,"generator_kw":0,"grid_inverter_kw":0},{"time":"2026-06-13 06:15:00","production_kw":0.008,"consumption_kw":0.4,"grid_kw":0.46,"battery_kw":0.078,"soc_pct":25.0,"pv_kw":0.008,"generator_kw":0,"grid_inverter_kw":0},{"time":"2026-06-13 06:20:00","production_kw":0.015,"consumption_kw":0.4,"grid_kw":0.46,"battery_kw":0.078,"soc_pct":25.0,"pv_kw":0.015,"generator_kw":0,"grid_inverter_kw":0},{"time":"2026-06-13 06:25:00","production_kw":0.035,"consumption_kw":0.4,"grid_kw":0.46,"battery_kw":0.076,"soc_pct":25.0,"pv_kw":0.035,"generator_kw":0,"grid_inverter_kw":0},{"time":"2026-06-13 06:30:00","production_kw":0.064,"consumption_kw":0.3,"grid_kw":0.36,"battery_kw":0.077,"soc_pct":25.0,"pv_kw":0.064,"generator_kw":0,"grid_inverter_kw":0},{"time":"2026-06-13 06:35:00","production_kw":0.078,"consumption_kw":0.29,"grid_kw":0.35,"battery_kw":0.075,"soc_pct":25.0,"pv_kw":0.078,"generator_kw":0,"grid_inverter_kw":0},{"time":"2026-06-13 06:40:00","production_kw":0.065,"consumption_kw":0.36,"grid_kw":0.42,"battery_kw":0.075,"soc_pct":25.0,"pv_kw":0.065,"generator_kw":0,"grid_inverter_kw":0},{"time":"2026-06-13 06:45:00","production_kw":0.067,"consumption_kw":0.35,"grid_kw":0.42,"battery_kw":0.068,"soc_pct":25.0,"pv_kw":0.067,"generator_kw":0,"grid_inverter_kw":0},{"time":"2026-06-13 06:50:00","production_kw":0.083,"consumption_kw":0.34,"grid_kw":0.4,"battery_kw":0.059,"soc_pct":25.0,"pv_kw":0.083,"generator_kw":0,"grid_inverter_kw":0},{"time":"2026-06-13 06:55:00","production_kw":0.11,"consumption_kw":0.31,"grid_kw":0.37,"battery_kw":0.046,"soc_pct":25.0,"pv_kw":0.11,"generator_kw":0,"grid_inverter_kw":0},{"time":"2026-06-13 07:00:00","production_kw":0.153,"consumption_kw":0.3,"grid_kw":0.37,"battery_kw":0.023,"soc_pct":25.0,"pv_kw":0.153,"generator_kw":0,"grid_inverter_kw":0},{"time":"2026-06-13 07:05:00","production_kw":0.157,"consumption_kw":0.29,"grid_kw":0.36,"battery_kw":0.017,"soc_pct":25.0,"pv_kw":0.157,"generator_kw":0,"grid_inverter_kw":0},{"time":"2026-06-13 07:10:00","production_kw":0.18,"consumption_kw":0.52,"grid_kw":0.58,"battery_kw":-0.005,"soc_pct":25.0,"pv_kw":0.18,"generator_kw":0,"grid_inverter_kw":0},{"time":"2026-06-13 07:15:00","production_kw":0.214,"consumption_kw":0.52,"grid_kw":0.58,"battery_kw":-0.027,"soc_pct":25.0,"pv_kw":0.214,"generator_kw":0,"grid_inverter_kw":0},{"time":"2026-06-13 07:20:00","production_kw":0.262,"consumption_kw":0.52,"grid_kw":0.58,"battery_kw":-0.058,"soc_pct":25.0,"pv_kw":0.262,"generator_kw":0,"grid_inverter_kw":0},{"time":"2026-06-13 07:25:00","production_kw":0.269,"consumption_kw":0.51,"grid_kw":0.58,"battery_kw":-0.079,"soc_pct":25.0,"pv_kw":0.269,"generator_kw":0,"grid_inverter_kw":0},{"time":"2026-06-13 07:30:00","production_kw":0.297,"consumption_kw":0.51,"grid_kw":0.57,"battery_kw":-0.091,"soc_pct":25.0,"pv_kw":0.297,"generator_kw":0,"grid_inverter_kw":0},{"time":"2026-06-13 07:35:00","production_kw":0.354,"consumption_kw":0.51,"grid_kw":0.57,"battery_kw":-0.158,"soc_pct":25.0,"pv_kw":0.354,"generator_kw":0,"grid_inverter_kw":0},{"time":"2026-06-13 07:40:00","production_kw":0.409,"consumption_kw":0.29,"grid_kw":0.36,"battery_kw":-0.226,"soc_pct":25.0,"pv_kw":0.409,"generator_kw":0,"grid_inverter_kw":0},{"time":"2026-06-13 07:45:00","production_kw":0.51,"consumption_kw":0.45,"grid_kw":0.18,"battery_kw":0.015,"soc_pct":25.0,"pv_kw":0.51,"generator_kw":0,"grid_inverter_kw":0},{"time":"2026-06-13 07:50:00","production_kw":0.599,"consumption_kw":0.46,"grid_kw":0.1,"battery_kw":0.016,"soc_pct":25.0,"pv_kw":0.599,"generator_kw":0,"grid_inverter_kw":0},{"time":"2026-06-13 07:55:00","production_kw":0.729,"consumption_kw":0.45,"grid_kw":0.0,"battery_kw":-0.023,"soc_pct":26.0,"pv_kw":0.729,"generator_kw":0,"grid_inverter_kw":0},{"time":"2026-06-13 08:00:00","production_kw":0.902,"consumption_kw":0.46,"grid_kw":0.02,"battery_kw":-0.213,"soc_pct":26.0,"pv_kw":0.902,"generator_kw":0,"grid_inverter_kw":0},{"time":"2026-06-13 08:05:00","production_kw":1.143,"consumption_kw":0.42,"grid_kw":0.0,"battery_kw":-0.46,"soc_pct":26.0,"pv_kw":1.143,"generator_kw":0,"grid_inverter_kw":0},{"time":"2026-06-13 08:10:00","production_kw":1.264,"consumption_kw":0.47,"grid_kw":0.02,"battery_kw":-0.551,"soc_pct":26.0,"pv_kw":1.264,"generator_kw":0,"grid_inverter_kw":0},{"time":"2026-06-13 08:15:00","production_kw":1.426,"consumption_kw":0.54,"grid_kw":0.02,"battery_kw":-0.643,"soc_pct":26.0,"pv_kw":1.426,"generator_kw":0,"grid_inverter_kw":0},{"time":"2026-06-13 08:20:00","production_kw":1.577,"consumption_kw":0.52,"grid_kw":0.0,"battery_kw":-0.788,"soc_pct":27.0,"pv_kw":1.577,"generator_kw":0,"grid_inverter_kw":0},{"time":"2026-06-13 08:25:00","production_kw":1.711,"consumption_kw":0.54,"grid_kw":0.02,"battery_kw":-0.919,"soc_pct":27.0,"pv_kw":1.711,"generator_kw":0,"grid_inverter_kw":0},{"time":"2026-06-13 08:30:00","production_kw":1.833,"consumption_kw":0.38,"grid_kw":0.0,"battery_kw":-1.183,"soc_pct":28.0,"pv_kw":1.833,"generator_kw":0,"grid_inverter_kw":0},{"time":"2026-06-13 08:35:00","production_kw":1.916,"consumption_kw":0.38,"grid_kw":0.0,"battery_kw":-1.268,"soc_pct":28.0,"pv_kw":1.916,"generator_kw":0,"grid_inverter_kw":0},{"time":"2026-06-13 08:40:00","production_kw":2.028,"consumption_kw":0.35,"grid_kw":0.0,"battery_kw":-1.411,"soc_pct":29.0,"pv_kw":2.028,"generator_kw":0,"grid_inverter_kw":0},{"time":"2026-06-13 08:45:00","production_kw":2.09,"consumption_kw":0.64,"grid_kw":0.08,"battery_kw":-1.264,"soc_pct":29.0,"pv_kw":2.09,"generator_kw":0,"grid_inverter_kw":0},{"time":"2026-06-13 08:50:00","production_kw":2.23,"consumption_kw":0.49,"grid_kw":0.0,"battery_kw":-1.465,"soc_pct":30.0,"pv_kw":2.23,"generator_kw":0,"grid_inverter_kw":0},{"time":"2026-06-13 08:55:00","production_kw":2.303,"consumption_kw":0.48,"grid_kw":0.0,"battery_kw":-1.546,"soc_pct":31.0,"pv_kw":2.303,"generator_kw":0,"grid_inverter_kw":0},{"time":"2026-06-13 09:00:00","production_kw":2.41,"consumption_kw":0.49,"grid_kw":0.02,"battery_kw":-1.667,"soc_pct":32.0,"pv_kw":2.41,"generator_kw":0,"grid_inverter_kw":0},{"time":"2026-06-13 09:05:00","production_kw":2.516,"consumption_kw":0.47,"grid_kw":0.02,"battery_kw":-1.787,"soc_pct":33.0,"pv_kw":2.516,"generator_kw":0,"grid_inverter_kw":0},{"time":"2026-06-13 09:10:00","production_kw":2.608,"consumption_kw":0.33,"grid_kw":0.0,"battery_kw":-2.007,"soc_pct":34.0,"pv_kw":2.608,"generator_kw":0,"grid_inverter_kw":0},{"time":"2026-06-13 09:15:00","production_kw":2.686,"consumption_kw":2.66,"grid_kw":0.02,"battery_kw":0.22,"soc_pct":34.0,"pv_kw":2.686,"generator_kw":0,"grid_inverter_kw":0},{"time":"2026-06-13 09:20:00","production_kw":2.727,"consumption_kw":2.6,"grid_kw":0.02,"battery_kw":0.13,"soc_pct":34.0,"pv_kw":2.727,"generator_kw":0,"grid_inverter_kw":0},{"time":"2026-06-13 09:25:00","production_kw":2.772,"consumption_kw":0.43,"grid_kw":0.0,"battery_kw":-2.069,"soc_pct":34.0,"pv_kw":2.772,"generator_kw":0,"grid_inverter_kw":0},{"time":"2026-06-13 09:30:00","production_kw":2.826,"consumption_kw":0.34,"grid_kw":0.02,"battery_kw":-2.219,"soc_pct":36.0,"pv_kw":2.826,"generator_kw":0,"grid_inverter_kw":0},{"time":"2026-06-13 09:35:00","production_kw":2.796,"consumption_kw":2.67,"grid_kw":0.0,"battery_kw":0.148,"soc_pct":36.0,"pv_kw":2.796,"generator_kw":0,"grid_inverter_kw":0},{"time":"2026-06-13 09:40:00","production_kw":2.607,"consumption_kw":2.75,"grid_kw":0.02,"battery_kw":0.394,"soc_pct":37.0,"pv_kw":2.607,"generator_kw":0,"grid_inverter_kw":0},{"time":"2026-06-13 09:45:00","production_kw":2.713,"consumption_kw":2.66,"grid_kw":0.0,"battery_kw":0.224,"soc_pct":37.0,"pv_kw":2.713,"generator_kw":0,"grid_inverter_kw":0},{"time":"2026-06-13 09:50:00","production_kw":2.792,"consumption_kw":2.6,"grid_kw":0.0,"battery_kw":0.079,"soc_pct":37.0,"pv_kw":2.792,"generator_kw":0,"grid_inverter_kw":0},{"time":"2026-06-13 09:55:00","production_kw":2.951,"consumption_kw":0.34,"grid_kw":0.0,"battery_kw":-2.33,"soc_pct":38.0,"pv_kw":2.951,"generator_kw":0,"grid_inverter_kw":0},{"time":"2026-06-13 10:00:00","production_kw":2.996,"consumption_kw":3.36,"grid_kw":0.0,"battery_kw":0.652,"soc_pct":38.0,"pv_kw":2.996,"generator_kw":0,"grid_inverter_kw":0},{"time":"2026-06-13 10:05:00","production_kw":2.989,"consumption_kw":3.34,"grid_kw":0.0,"battery_kw":0.639,"soc_pct":37.0,"pv_kw":2.989,"generator_kw":0,"grid_inverter_kw":0},{"time":"2026-06-13 10:10:00","production_kw":3.005,"consumption_kw":3.36,"grid_kw":0.02,"battery_kw":0.596,"soc_pct":37.0,"pv_kw":3.005,"generator_kw":0,"grid_inverter_kw":0},{"time":"2026-06-13 10:15:00","production_kw":3.081,"consumption_kw":3.34,"grid_kw":0.0,"battery_kw":0.549,"soc_pct":37.0,"pv_kw":3.081,"generator_kw":0,"grid_inverter_kw":0},{"time":"2026-06-13 10:20:00","production_kw":3.092,"consumption_kw":3.43,"grid_kw":0.02,"battery_kw":0.593,"soc_pct":36.0,"pv_kw":3.092,"generator_kw":0,"grid_inverter_kw":0},{"time":"2026-06-13 10:25:00","production_kw":3.139,"consumption_kw":3.4,"grid_kw":0.0,"battery_kw":0.533,"soc_pct":36.0,"pv_kw":3.139,"generator_kw":0,"grid_inverter_kw":0},{"time":"2026-06-13 10:30:00","production_kw":3.155,"consumption_kw":3.44,"grid_kw":0.02,"battery_kw":0.542,"soc_pct":36.0,"pv_kw":3.155,"generator_kw":0,"grid_inverter_kw":0},{"time":"2026-06-13 10:35:00","production_kw":3.154,"consumption_kw":3.37,"grid_kw":0.02,"battery_kw":0.473,"soc_pct":36.0,"pv_kw":3.154,"generator_kw":0,"grid_inverter_kw":0},{"time":"2026-06-13 10:40:00","production_kw":3.249,"consumption_kw":3.32,"grid_kw":0.0,"battery_kw":0.36,"soc_pct":35.0,"pv_kw":3.249,"generator_kw":0,"grid_inverter_kw":0},{"time":"2026-06-13 10:45:00","production_kw":3.302,"consumption_kw":3.35,"grid_kw":0.0,"battery_kw":0.324,"soc_pct":35.0,"pv_kw":3.302,"generator_kw":0,"grid_inverter_kw":0},{"time":"2026-06-13 10:50:00","production_kw":3.379,"consumption_kw":3.32,"grid_kw":0.02,"battery_kw":0.217,"soc_pct":35.0,"pv_kw":3.379,"generator_kw":0,"grid_inverter_kw":0},{"time":"2026-06-13 10:55:00","production_kw":3.441,"consumption_kw":3.35,"grid_kw":0.02,"battery_kw":0.173,"soc_pct":35.0,"pv_kw":3.441,"generator_kw":0,"grid_inverter_kw":0},{"time":"2026-06-13 11:00:00","production_kw":3.422,"consumption_kw":3.35,"grid_kw":0.02,"battery_kw":0.178,"soc_pct":35.0,"pv_kw":3.422,"generator_kw":0,"grid_inverter_kw":0},{"time":"2026-06-13 11:05:00","production_kw":3.433,"consumption_kw":3.34,"grid_kw":0.02,"battery_kw":0.16,"soc_pct":35.0,"pv_kw":3.433,"generator_kw":0,"grid_inverter_kw":0},{"time":"2026-06-13 11:10:00","production_kw":3.476,"consumption_kw":3.45,"grid_kw":0.0,"battery_kw":0.258,"soc_pct":35.0,"pv_kw":3.476,"generator_kw":0,"grid_inverter_kw":0},{"time":"2026-06-13 11:15:00","production_kw":3.539,"consumption_kw":3.53,"grid_kw":0.03,"battery_kw":0.241,"soc_pct":35.0,"pv_kw":3.539,"generator_kw":0,"grid_inverter_kw":0},{"time":"2026-06-13 11:20:00","production_kw":3.533,"consumption_kw":3.44,"grid_kw":0.03,"battery_kw":0.152,"soc_pct":35.0,"pv_kw":3.533,"generator_kw":0,"grid_inverter_kw":0},{"time":"2026-06-13 11:25:00","production_kw":3.555,"consumption_kw":0.26,"grid_kw":0.0,"battery_kw":-3.006,"soc_pct":35.0,"pv_kw":3.555,"generator_kw":0,"grid_inverter_kw":0},{"time":"2026-06-13 11:30:00","production_kw":3.606,"consumption_kw":0.29,"grid_kw":0.02,"battery_kw":-3.052,"soc_pct":37.0,"pv_kw":3.606,"generator_kw":0,"grid_inverter_kw":0},{"time":"2026-06-13 11:35:00","production_kw":3.533,"consumption_kw":0.28,"grid_kw":0.02,"battery_kw":-2.986,"soc_pct":38.0,"pv_kw":3.533,"generator_kw":0,"grid_inverter_kw":0},{"time":"2026-06-13 11:40:00","production_kw":3.657,"consumption_kw":0.28,"grid_kw":0.02,"battery_kw":-3.107,"soc_pct":40.0,"pv_kw":3.657,"generator_kw":0,"grid_inverter_kw":0},{"time":"2026-06-13 11:45:00","production_kw":3.679,"consumption_kw":0.26,"grid_kw":0.0,"battery_kw":-3.115,"soc_pct":42.0,"pv_kw":3.679,"generator_kw":0,"grid_inverter_kw":0},{"time":"2026-06-13 11:50:00","production_kw":3.652,"consumption_kw":0.28,"grid_kw":0.02,"battery_kw":-3.092,"soc_pct":43.0,"pv_kw":3.652,"generator_kw":0,"grid_inverter_kw":0},{"time":"2026-06-13 11:55:00","production_kw":3.63,"consumption_kw":0.44,"grid_kw":0.0,"battery_kw":-2.906,"soc_pct":45.0,"pv_kw":3.63,"generator_kw":0,"grid_inverter_kw":0},{"time":"2026-06-13 12:00:00","production_kw":3.603,"consumption_kw":0.39,"grid_kw":0.02,"battery_kw":-2.938,"soc_pct":47.0,"pv_kw":3.603,"generator_kw":0,"grid_inverter_kw":0},{"time":"2026-06-13 12:05:00","production_kw":3.588,"consumption_kw":0.4,"grid_kw":0.0,"battery_kw":-2.891,"soc_pct":48.0,"pv_kw":3.588,"generator_kw":0,"grid_inverter_kw":0},{"time":"2026-06-13 12:10:00","production_kw":3.582,"consumption_kw":0.4,"grid_kw":0.02,"battery_kw":-2.894,"soc_pct":50.0,"pv_kw":3.582,"generator_kw":0,"grid_inverter_kw":0},{"time":"2026-06-13 12:15:00","production_kw":3.605,"consumption_kw":0.33,"grid_kw":0.0,"battery_kw":-2.967,"soc_pct":51.0,"pv_kw":3.605,"generator_kw":0,"grid_inverter_kw":0},{"time":"2026-06-13 12:20:00","production_kw":3.514,"consumption_kw":0.28,"grid_kw":0.02,"battery_kw":-2.949,"soc_pct":53.0,"pv_kw":3.514,"generator_kw":0,"grid_inverter_kw":0},{"time":"2026-06-13 12:25:00","production_kw":3.516,"consumption_kw":4.29,"grid_kw":0.0,"battery_kw":1.092,"soc_pct":53.0,"pv_kw":3.516,"generator_kw":0,"grid_inverter_kw":0},{"time":"2026-06-13 12:30:00","production_kw":3.506,"consumption_kw":1.26,"grid_kw":0.02,"battery_kw":-1.989,"soc_pct":54.0,"pv_kw":3.506,"generator_kw":0,"grid_inverter_kw":0},{"time":"2026-06-13 12:35:00","production_kw":3.468,"consumption_kw":1.23,"grid_kw":0.0,"battery_kw":-1.947,"soc_pct":55.0,"pv_kw":3.468,"generator_kw":0,"grid_inverter_kw":0},{"time":"2026-06-13 12:40:00","production_kw":3.527,"consumption_kw":1.25,"grid_kw":0.02,"battery_kw":-2.015,"soc_pct":56.0,"pv_kw":3.527,"generator_kw":0,"grid_inverter_kw":0},{"time":"2026-06-13 12:45:00","production_kw":3.524,"consumption_kw":1.22,"grid_kw":0.0,"battery_kw":-2.026,"soc_pct":57.0,"pv_kw":3.524,"generator_kw":0,"grid_inverter_kw":0},{"time":"2026-06-13 12:50:00","production_kw":3.485,"consumption_kw":1.2,"grid_kw":0.02,"battery_kw":-2.016,"soc_pct":58.0,"pv_kw":3.485,"generator_kw":0,"grid_inverter_kw":0},{"time":"2026-06-13 12:55:00","production_kw":3.447,"consumption_kw":1.29,"grid_kw":0.0,"battery_kw":-1.873,"soc_pct":59.0,"pv_kw":3.447,"generator_kw":0,"grid_inverter_kw":0},{"time":"2026-06-13 13:00:00","production_kw":3.581,"consumption_kw":1.32,"grid_kw":0.02,"battery_kw":-2.003,"soc_pct":60.0,"pv_kw":3.581,"generator_kw":0,"grid_inverter_kw":0},{"time":"2026-06-13 13:05:00","production_kw":3.549,"consumption_kw":1.27,"grid_kw":0.02,"battery_kw":-2.029,"soc_pct":61.0,"pv_kw":3.549,"generator_kw":0,"grid_inverter_kw":0},{"time":"2026-06-13 13:10:00","production_kw":3.521,"consumption_kw":1.24,"grid_kw":0.02,"battery_kw":-2.023,"soc_pct":62.0,"pv_kw":3.521,"generator_kw":0,"grid_inverter_kw":0},{"time":"2026-06-13 13:15:00","production_kw":3.518,"consumption_kw":1.23,"grid_kw":0.02,"battery_kw":-1.999,"soc_pct":63.0,"pv_kw":3.518,"generator_kw":0,"grid_inverter_kw":0},{"time":"2026-06-13 13:20:00","production_kw":3.441,"consumption_kw":1.24,"grid_kw":0.02,"battery_kw":-1.948,"soc_pct":64.0,"pv_kw":3.441,"generator_kw":0,"grid_inverter_kw":0},{"time":"2026-06-13 13:25:00","production_kw":3.447,"consumption_kw":1.21,"grid_kw":0.0,"battery_kw":-1.949,"soc_pct":65.0,"pv_kw":3.447,"generator_kw":0,"grid_inverter_kw":0},{"time":"2026-06-13 13:30:00","production_kw":3.365,"consumption_kw":1.11,"grid_kw":0.02,"battery_kw":-1.986,"soc_pct":66.0,"pv_kw":3.365,"generator_kw":0,"grid_inverter_kw":0},{"time":"2026-06-13 13:35:00","production_kw":3.303,"consumption_kw":1.11,"grid_kw":0.02,"battery_kw":-1.942,"soc_pct":67.0,"pv_kw":3.303,"generator_kw":0,"grid_inverter_kw":0},{"time":"2026-06-13 13:40:00","production_kw":3.252,"consumption_kw":1.08,"grid_kw":0.0,"battery_kw":-1.894,"soc_pct":68.0,"pv_kw":3.252,"generator_kw":0,"grid_inverter_kw":0},{"time":"2026-06-13 13:45:00","production_kw":3.221,"consumption_kw":1.13,"grid_kw":0.02,"battery_kw":-1.845,"soc_pct":69.0,"pv_kw":3.221,"generator_kw":0,"grid_inverter_kw":0},{"time":"2026-06-13 13:50:00","production_kw":3.133,"consumption_kw":1.12,"grid_kw":0.02,"battery_kw":-1.766,"soc_pct":70.0,"pv_kw":3.133,"generator_kw":0,"grid_inverter_kw":0},{"time":"2026-06-13 13:55:00","production_kw":3.082,"consumption_kw":1.11,"grid_kw":0.0,"battery_kw":-1.713,"soc_pct":71.0,"pv_kw":3.082,"generator_kw":0,"grid_inverter_kw":0},{"time":"2026-06-13 14:00:00","production_kw":3.008,"consumption_kw":1.1,"grid_kw":0.0,"battery_kw":-1.634,"soc_pct":72.0,"pv_kw":3.008,"generator_kw":0,"grid_inverter_kw":0},{"time":"2026-06-13 14:05:00","production_kw":2.989,"consumption_kw":1.1,"grid_kw":0.0,"battery_kw":-1.62,"soc_pct":73.0,"pv_kw":2.989,"generator_kw":0,"grid_inverter_kw":0},{"time":"2026-06-13 14:10:00","production_kw":2.953,"consumption_kw":1.17,"grid_kw":0.02,"battery_kw":-1.523,"soc_pct":73.0,"pv_kw":2.953,"generator_kw":0,"grid_inverter_kw":0},{"time":"2026-06-13 14:15:00","production_kw":2.916,"consumption_kw":1.19,"grid_kw":0.02,"battery_kw":-1.468,"soc_pct":74.0,"pv_kw":2.916,"generator_kw":0,"grid_inverter_kw":0},{"time":"2026-06-13 14:20:00","production_kw":2.799,"consumption_kw":1.17,"grid_kw":0.02,"battery_kw":-1.377,"soc_pct":75.0,"pv_kw":2.799,"generator_kw":0,"grid_inverter_kw":0},{"time":"2026-06-13 14:25:00","production_kw":2.746,"consumption_kw":1.18,"grid_kw":0.02,"battery_kw":-1.319,"soc_pct":76.0,"pv_kw":2.746,"generator_kw":0,"grid_inverter_kw":0},{"time":"2026-06-13 14:30:00","production_kw":2.667,"consumption_kw":1.15,"grid_kw":0.0,"battery_kw":-1.244,"soc_pct":76.0,"pv_kw":2.667,"generator_kw":0,"grid_inverter_kw":0},{"time":"2026-06-13 14:35:00","production_kw":2.588,"consumption_kw":1.17,"grid_kw":0.02,"battery_kw":-1.17,"soc_pct":77.0,"pv_kw":2.588,"generator_kw":0,"grid_inverter_kw":0},{"time":"2026-06-13 14:40:00","production_kw":2.528,"consumption_kw":1.16,"grid_kw":0.02,"battery_kw":-1.108,"soc_pct":78.0,"pv_kw":2.528,"generator_kw":0,"grid_inverter_kw":0},{"time":"2026-06-13 14:45:00","production_kw":2.455,"consumption_kw":1.29,"grid_kw":0.0,"battery_kw":-0.899,"soc_pct":78.0,"pv_kw":2.455,"generator_kw":0,"grid_inverter_kw":0},{"time":"2026-06-13 14:50:00","production_kw":2.388,"consumption_kw":1.3,"grid_kw":0.02,"battery_kw":-0.817,"soc_pct":79.0,"pv_kw":2.388,"generator_kw":0,"grid_inverter_kw":0},{"time":"2026-06-13 14:55:00","production_kw":2.304,"consumption_kw":1.31,"grid_kw":0.02,"battery_kw":-0.742,"soc_pct":79.0,"pv_kw":2.304,"generator_kw":0,"grid_inverter_kw":0},{"time":"2026-06-13 15:00:00","production_kw":1.87,"consumption_kw":4.37,"grid_kw":0.0,"battery_kw":2.84,"soc_pct":78.0,"pv_kw":1.87,"generator_kw":0,"grid_inverter_kw":0},{"time":"2026-06-13 15:05:00","production_kw":1.682,"consumption_kw":4.35,"grid_kw":0.0,"battery_kw":3.011,"soc_pct":76.0,"pv_kw":1.682,"generator_kw":0,"grid_inverter_kw":0},{"time":"2026-06-13 15:10:00","production_kw":1.358,"consumption_kw":4.35,"grid_kw":0.0,"battery_kw":3.332,"soc_pct":74.0,"pv_kw":1.358,"generator_kw":0,"grid_inverter_kw":0},{"time":"2026-06-13 15:15:00","production_kw":1.008,"consumption_kw":4.4,"grid_kw":0.02,"battery_kw":3.709,"soc_pct":73.0,"pv_kw":1.008,"generator_kw":0,"grid_inverter_kw":0},{"time":"2026-06-13 15:20:00","production_kw":0.865,"consumption_kw":4.27,"grid_kw":0.02,"battery_kw":3.73,"soc_pct":71.0,"pv_kw":0.865,"generator_kw":0,"grid_inverter_kw":0},{"time":"2026-06-13 15:25:00","production_kw":0.654,"consumption_kw":4.26,"grid_kw":0.02,"battery_kw":3.958,"soc_pct":68.0,"pv_kw":0.654,"generator_kw":0,"grid_inverter_kw":0},{"time":"2026-06-13 15:30:00","production_kw":0.547,"consumption_kw":1.19,"grid_kw":0.02,"battery_kw":0.874,"soc_pct":68.0,"pv_kw":0.547,"generator_kw":0,"grid_inverter_kw":0},{"time":"2026-06-13 15:35:00","production_kw":0.444,"consumption_kw":1.19,"grid_kw":0.02,"battery_kw":0.975,"soc_pct":68.0,"pv_kw":0.444,"generator_kw":0,"grid_inverter_kw":0},{"time":"2026-06-13 15:40:00","production_kw":0.357,"consumption_kw":1.15,"grid_kw":0.0,"battery_kw":1.037,"soc_pct":67.0,"pv_kw":0.357,"generator_kw":0,"grid_inverter_kw":0},{"time":"2026-06-13 15:45:00","production_kw":0.376,"consumption_kw":1.16,"grid_kw":0.02,"battery_kw":1.026,"soc_pct":66.0,"pv_kw":0.376,"generator_kw":0,"grid_inverter_kw":0},{"time":"2026-06-13 15:50:00","production_kw":0.451,"consumption_kw":1.17,"grid_kw":0.02,"battery_kw":0.954,"soc_pct":66.0,"pv_kw":0.451,"generator_kw":0,"grid_inverter_kw":0},{"time":"2026-06-13 15:55:00","production_kw":0.687,"consumption_kw":1.3,"grid_kw":0.02,"battery_kw":0.853,"soc_pct":66.0,"pv_kw":0.687,"generator_kw":0,"grid_inverter_kw":0},{"time":"2026-06-13 16:00:00","production_kw":0.706,"consumption_kw":1.28,"grid_kw":0.0,"battery_kw":0.849,"soc_pct":65.0,"pv_kw":0.706,"generator_kw":0,"grid_inverter_kw":0},{"time":"2026-06-13 16:05:00","production_kw":0.945,"consumption_kw":1.27,"grid_kw":0.0,"battery_kw":0.594,"soc_pct":65.0,"pv_kw":0.945,"generator_kw":0,"grid_inverter_kw":0},{"time":"2026-06-13 16:10:00","production_kw":0.888,"consumption_kw":1.27,"grid_kw":0.0,"battery_kw":0.638,"soc_pct":64.0,"pv_kw":0.888,"generator_kw":0,"grid_inverter_kw":0},{"time":"2026-06-13 16:15:00","production_kw":0.844,"consumption_kw":1.16,"grid_kw":0.0,"battery_kw":0.577,"soc_pct":64.0,"pv_kw":0.844,"generator_kw":0,"grid_inverter_kw":0},{"time":"2026-06-13 16:20:00","production_kw":0.791,"consumption_kw":1.15,"grid_kw":0.0,"battery_kw":0.616,"soc_pct":64.0,"pv_kw":0.791,"generator_kw":0,"grid_inverter_kw":0},{"time":"2026-06-13 16:25:00","production_kw":0.747,"consumption_kw":1.17,"grid_kw":0.0,"battery_kw":0.678,"soc_pct":63.0,"pv_kw":0.747,"generator_kw":0,"grid_inverter_kw":0},{"time":"2026-06-13 16:30:00","production_kw":0.452,"consumption_kw":1.19,"grid_kw":0.02,"battery_kw":0.984,"soc_pct":63.0,"pv_kw":0.452,"generator_kw":0,"grid_inverter_kw":0},{"time":"2026-06-13 16:35:00","production_kw":0.248,"consumption_kw":0.34,"grid_kw":0.02,"battery_kw":0.314,"soc_pct":62.0,"pv_kw":0.248,"generator_kw":0,"grid_inverter_kw":0},{"time":"2026-06-13 16:40:00","production_kw":0.266,"consumption_kw":1.17,"grid_kw":0.02,"battery_kw":1.141,"soc_pct":62.0,"pv_kw":0.266,"generator_kw":0,"grid_inverter_kw":0},{"time":"2026-06-13 16:45:00","production_kw":0.243,"consumption_kw":1.14,"grid_kw":0.0,"battery_kw":1.16,"soc_pct":61.0,"pv_kw":0.243,"generator_kw":0,"grid_inverter_kw":0},{"time":"2026-06-13 16:50:00","production_kw":0.227,"consumption_kw":1.17,"grid_kw":0.0,"battery_kw":1.209,"soc_pct":61.0,"pv_kw":0.227,"generator_kw":0,"grid_inverter_kw":0},{"time":"2026-06-13 16:55:00","production_kw":0.197,"consumption_kw":1.34,"grid_kw":0.02,"battery_kw":1.387,"soc_pct":60.0,"pv_kw":0.197,"generator_kw":0,"grid_inverter_kw":0},{"time":"2026-06-13 17:00:00","production_kw":0.137,"consumption_kw":1.36,"grid_kw":0.02,"battery_kw":1.436,"soc_pct":59.0,"pv_kw":0.137,"generator_kw":0,"grid_inverter_kw":0},{"time":"2026-06-13 17:05:00","production_kw":0.118,"consumption_kw":1.24,"grid_kw":0.02,"battery_kw":1.328,"soc_pct":59.0,"pv_kw":0.118,"generator_kw":0,"grid_inverter_kw":0},{"time":"2026-06-13 17:10:00","production_kw":0.073,"consumption_kw":1.24,"grid_kw":0.02,"battery_kw":1.35,"soc_pct":58.0,"pv_kw":0.073,"generator_kw":0,"grid_inverter_kw":0},{"time":"2026-06-13 17:15:00","production_kw":0.062,"consumption_kw":1.12,"grid_kw":0.0,"battery_kw":1.249,"soc_pct":57.0,"pv_kw":0.062,"generator_kw":0,"grid_inverter_kw":0},{"time":"2026-06-13 17:20:00","production_kw":0.051,"consumption_kw":1.12,"grid_kw":0.02,"battery_kw":1.237,"soc_pct":57.0,"pv_kw":0.051,"generator_kw":0,"grid_inverter_kw":0},{"time":"2026-06-13 17:25:00","production_kw":0.042,"consumption_kw":1.1,"grid_kw":0.0,"battery_kw":1.245,"soc_pct":56.0,"pv_kw":0.042,"generator_kw":0,"grid_inverter_kw":0},{"time":"2026-06-13 17:30:00","production_kw":0.055,"consumption_kw":1.16,"grid_kw":0.0,"battery_kw":1.309,"soc_pct":55.0,"pv_kw":0.055,"generator_kw":0,"grid_inverter_kw":0},{"time":"2026-06-13 17:35:00","production_kw":0.082,"consumption_kw":1.24,"grid_kw":0.02,"battery_kw":1.368,"soc_pct":55.0,"pv_kw":0.082,"generator_kw":0,"grid_inverter_kw":0},{"time":"2026-06-13 17:40:00","production_kw":0.057,"consumption_kw":1.31,"grid_kw":0.02,"battery_kw":1.441,"soc_pct":54.0,"pv_kw":0.057,"generator_kw":0,"grid_inverter_kw":0},{"time":"2026-06-13 17:45:00","production_kw":0.031,"consumption_kw":1.33,"grid_kw":0.0,"battery_kw":1.478,"soc_pct":53.0,"pv_kw":0.031,"generator_kw":0,"grid_inverter_kw":0},{"time":"2026-06-13 17:50:00","production_kw":0.011,"consumption_kw":1.34,"grid_kw":0.02,"battery_kw":1.474,"soc_pct":52.0,"pv_kw":0.011,"generator_kw":0,"grid_inverter_kw":0},{"time":"2026-06-13 17:55:00","production_kw":0.011,"consumption_kw":1.34,"grid_kw":0.02,"battery_kw":1.474,"soc_pct":52.0,"pv_kw":0.011,"generator_kw":0,"grid_inverter_kw":0},{"time":"2026-06-13 17:55:51","production_kw":0.01,"consumption_kw":1.34,"grid_kw":0.02,"battery_kw":1.471,"soc_pct":52.0,"pv_kw":0.01,"generator_kw":0,"grid_inverter_kw":0}]}